jbssdk/BaseClient.py
jbssdk/Client.py
jbssdk/Consts.py
jbssdk/__init__.py
jbssdk/Model/Response.py
jbssdk/Model/__init__.py
jbssdk/Model/deals/__init__.py
jbssdk/Model/deals/dealAfterExitStrategy.py
jbssdk/Model/deals/dealAfterInitialCase.py
jbssdk/Model/deals/dealAfterInvestmentCaseDetail.py
jbssdk/Model/deals/dealAfterReviseCase.py
jbssdk/Model/deals/dealCaptable.py
jbssdk/Model/deals/dealCaptableDetail.py
jbssdk/Model/deals/dealCashFlow.py
jbssdk/Model/deals/dealInfo.py
jbssdk/Model/deals/dealInvestment.py
jbssdk/Model/deals/dealInvestmentEvaluation.py
jbssdk/Model/deals/dealMeeting.py
jbssdk/Model/deals/dealPCW.py
jbssdk/Model/deals/dealTerms.py
jbssdk/Model/deals/dealTrack.py
jbssdk/Model/deals/dealValuation.py
jbssdk/Model/deals/dealValuationInvestment.py
jbssdk/Model/funds/__init__.py
jbssdk/Model/funds/fundBaseCashFlow.py
jbssdk/Model/funds/fundBaseDealCashFlow.py
jbssdk/Model/funds/fundBaseExpense.py
jbssdk/Model/funds/fundBaseIncome.py
jbssdk/Model/funds/fundBaseInfo.py
jbssdk/Model/funds/fundBaseInfoPhase.py
jbssdk/Model/funds/fundBaseInvestor.py
jbssdk/Model/funds/fundBaseInvestorLPA.py
jbssdk/Model/funds/fundBaseLPCashFlow.py
jbssdk/Model/funds/fundBaseValuation.py
jbssdk/Model/gp/__init__.py
jbssdk/Model/gp/gpBaseFund.py
jbssdk/Model/gp/gpBaseInfo.py
jbssdk/Model/inner_api/BaseParams.py
jbssdk/Model/inner_api/__init__.py
jbssdk/Model/lp/__init__.py
jbssdk/Model/lp/lpBaseInfo.py
jbssdk/Model/lp/lpBaseInvestor.py
jbssdk/Model/lp/lpBaseTrack.py
jbssdk/Model/system/__init__.py
jbssdk/Model/system/hrbase.py
jbssdk/Model/system/rate.py
jbssdk/Model/system/rateDetail.py
jbssdk/mutation/MutationClient.py
jbssdk/mutation/__init__.py
jbssdk/mutation/Model/DeptAndUser.py
jbssdk/mutation/consts/Currency.py
jbssdk/mutation/consts/FundingRound.py
jbssdk/mutation/consts/Partners.py
jbssdk/mutation/consts/__init__.py
jbssdk/mutation/lib/__init__.py
jbssdk/mutation/lib/processFile.py
jbssdk/mutation/lib/processUser.py
jbssdk/utlils/__init__.py
jbssdk-0.0.8.dist-info/METADATA
jbssdk-0.0.8.dist-info/WHEEL
jbssdk-0.0.8.dist-info/top_level.txt
jbssdk-0.0.8.dist-info/RECORD
