Metadata-Version: 2.4
Name: jbssdk
Version: 0.0.8
Summary: A small example package
Author-email: Licheng Zhou <licheng.zhou@cathay.fr>
Classifier: Programming Language :: Python :: 3
Classifier: License :: OSI Approved :: MIT License
Requires-Python: >=3.10
Requires-Dist: dotenv>=0.9.9
Requires-Dist: httpx>=0.28.1
Requires-Dist: markdown>=3.8.2
Requires-Dist: pydantic>=2.11.7
